creative_writer_cli/__init__.py
creative_writer_cli/cli.py
creative_writer_cli/core/__init__.py
creative_writer_cli/core/models.py
creative_writer_cli/core/templates.py
creative_writer_cli/data/__init__.py
creative_writer_cli/data/repositories/__init__.py
creative_writer_cli/data/repositories/json_store.py
creative_writer_cli/data/repositories/project_repository.py
creative_writer_cli/ui/__init__.py
creative_writer_cli/ui/ascii_art.py
creative_writer_cli/ui/cli_app.py
creative_writer_cli/ui/display.py
creative_writer_cli/ui/wizards.py
creative_writer_cli/ui/display/__init__.py
creative_writer_cli/ui/display/tables.py
creative_writer_cli/ui/display/views.py
creative_writer_cli/ui/section_handlers/__init__.py
creative_writer_cli/ui/section_handlers/base_section_handler.py
creative_writer_cli/ui/section_handlers/chapter_handler.py
creative_writer_cli/ui/section_handlers/character_handler.py
creative_writer_cli/ui/section_handlers/generic_handler.py
creative_writer_cli/ui/section_handlers/notes_handler.py
creative_writer_cli/ui/section_handlers/plot_handler.py
creative_writer_cli/ui/section_handlers/reference_handler.py
creative_writer_cli/ui/section_handlers/scientific_text_handler.py
creative_writer_cli/ui/section_handlers/theme_handler.py
creative_writer_cli/ui/section_handlers/worldbuilding_handler.py
creative_writer_cli/ui/services/__init__.py
creative_writer_cli/ui/services/project_interaction_service.py
creative_writer_cli/ui/wizards/__init__.py
creative_writer_cli/ui/wizards/generic_wizards.py
creative_writer_cli/ui/wizards/novel_wizards.py
creative_writer_cli/ui/wizards/scientific_wizards.py
creative_writer_cli/utils/config_manager.py
creative_writer_cli/utils/export_formatter.py
creative_writer_cli/utils/path_helpers.py
creative_writer_cli/utils/reference_export_formatter.py
creative_writer_cli/utils/word_counter.py
creative_writer_cli-0.1.2.dist-info/licenses/LICENSE
creative_writer_cli-0.1.2.dist-info/METADATA
creative_writer_cli-0.1.2.dist-info/WHEEL
creative_writer_cli-0.1.2.dist-info/entry_points.txt
creative_writer_cli-0.1.2.dist-info/top_level.txt
creative_writer_cli-0.1.2.dist-info/RECORD
