Metadata-Version: 2.4
Name: creative-writer-cli
Version: 0.1.2
Summary: A minimalistic CLI tool for creative writing project management.
Author-email: Daniel Wieser <your.email@example.com>
License: MIT License
Keywords: cli,writing,project-management,creative
Classifier: Programming Language :: Python :: 3
Classifier: License :: OSI Approved :: MIT License
Classifier: Operating System :: OS Independent
Classifier: Environment :: Console
Classifier: Intended Audience :: End Users/Desktop
Classifier: Topic :: Text Processing :: General
Requires-Python: >=3.8
License-File: LICENSE
Requires-Dist: markdown-it-py==3.0.0
Requires-Dist: mdurl==0.1.2
Requires-Dist: prompt_toolkit==3.0.51
Requires-Dist: Pygments==2.19.2
Requires-Dist: questionary==2.1.0
Requires-Dist: rich==14.0.0
Requires-Dist: wcwidth==0.2.13
Requires-Dist: requests
Dynamic: license-file
